hexgonulator/__init__.py
hexgonulator/common/__init__.py
hexgonulator/common/bits_ops.py
hexgonulator/memory/__init__.py
hexgonulator/memory/abstract.py
hexgonulator/memory/controller.py
hexgonulator/memory/hub.py
hexgonulator/memory/ram.py
hexgonulator/v67/__init__.py
hexgonulator/v67/processor.py
hexgonulator/v67/registers.py
hexgonulator/v67/sequencer.py
hexgonulator/v67/xunits.py
hexgonulator/v67/core_registers/__init__.py
hexgonulator/v67/core_registers/modifier_register.py
hexgonulator/v67/core_registers/user_status_register.py
hexgonulator/v67/instructions/__init__.py
hexgonulator/v67/instructions/instruction.py
hexgonulator/v67/instructions/abstract/__init__.py
hexgonulator/v67/instructions/abstract/add.py
hexgonulator/v67/instructions/abstract/add_to_pc.py
hexgonulator/v67/instructions/abstract/all8.py
hexgonulator/v67/instructions/abstract/and_.py
hexgonulator/v67/instructions/abstract/and_not.py
hexgonulator/v67/instructions/abstract/any8.py
hexgonulator/v67/instructions/abstract/aslh.py
hexgonulator/v67/instructions/abstract/asrh.py
hexgonulator/v67/instructions/abstract/call.py
hexgonulator/v67/instructions/abstract/callr.py
hexgonulator/v67/instructions/abstract/cmp_eq.py
hexgonulator/v67/instructions/abstract/cmp_eq_and_jump.py
hexgonulator/v67/instructions/abstract/cmp_gt.py
hexgonulator/v67/instructions/abstract/cmp_gt_and_jump.py
hexgonulator/v67/instructions/abstract/cmp_gtu.py
hexgonulator/v67/instructions/abstract/cmp_gtu_and_jump.py
hexgonulator/v67/instructions/abstract/combine_halfwords.py
hexgonulator/v67/instructions/abstract/combine_words.py
hexgonulator/v67/instructions/abstract/conditional_add.py
hexgonulator/v67/instructions/abstract/conditional_and.py
hexgonulator/v67/instructions/abstract/conditional_aslh.py
hexgonulator/v67/instructions/abstract/conditional_asrh.py
hexgonulator/v67/instructions/abstract/conditional_call.py
hexgonulator/v67/instructions/abstract/conditional_callr.py
hexagonulator-0.0.1.dist-info/LICENSE
hexagonulator-0.0.1.dist-info/METADATA
hexagonulator-0.0.1.dist-info/WHEEL
hexagonulator-0.0.1.dist-info/top_level.txt
hexagonulator-0.0.1.dist-info/RECORD
