Metadata-Version: 2.1
Name: hexagonulator
Version: 0.0.1
Summary: Python emulator for hexagon
Author: Matan Perelman
Author-email: matan1008@gmail.com
License: GNU GENERAL PUBLIC LICENSE
Project-URL: Homepage, https://github.com/matan1008/hexagonulator
Project-URL: Source, https://github.com/matan1008/hexagonulator
Classifier: Programming Language :: Python :: 3.7
Classifier: Programming Language :: Python :: 3.8
Classifier: Programming Language :: Python :: 3.9
Classifier: Programming Language :: Python :: 3.10
Classifier: Programming Language :: Python :: 3.11
Requires-Python: >=3.7
License-File: LICENSE
Provides-Extra: testing
Requires-Dist: pytest ; extra == 'testing'
